Metadata-Version: 2.1
Name: email-smtp
Version: 1.0.1
Summary: UNKNOWN
Home-page: https://github.com/ouroboroscoding/email-smtp-python
Author: Chris Nasr - Ouroboros Coding Inc.
Author-email: chris@ouroboroscoding.com
License: MIT
Project-URL: Source, https://github.com/ouroboroscoding/email-smtp-python
Project-URL: Tracker, https://github.com/ouroboroscoding/email-smtp-python/issues
Keywords: json
Platform: UNKNOWN
Requires-Python: >=3.10
License-File: LICENSE
